README.rst
setup.py
wagtail_cloudfront_invalidate/__init__.py
wagtail_cloudfront_invalidate/apps.py
wagtail_cloudfront_invalidate/invalidate.py
wagtail_cloudfront_invalidate/models.py
wagtail_cloudfront_invalidate/wagtail_hooks.py
wagtail_cloudfront_invalidate.egg-info/PKG-INFO
wagtail_cloudfront_invalidate.egg-info/SOURCES.txt
wagtail_cloudfront_invalidate.egg-info/dependency_links.txt
wagtail_cloudfront_invalidate.egg-info/requires.txt
wagtail_cloudfront_invalidate.egg-info/top_level.txt