Metadata-Version: 1.1
Name: wagtail-cloudfront-invalidate
Version: 1.1.2
Summary: A wagtail hook to invalidate AWS's CloudFront cache when a page is updated
Home-page: https://github.com/ryanbagwell/wagtail-cloudfront-invalidate/
Author: Ryan Bagwell
Author-email: ryan@ryanbagwell.com
License: UNKNOWN
Platform: UNKNOWN
Classifier: Environment :: Web Environment
Classifier: Framework :: Django
Classifier: Intended Audience :: Developers
Classifier: Programming Language :: Python
Classifier: Topic :: Internet :: WWW/HTTP
